<annotation verified="yes">
                                    <folder>Annotation</folder>
                                    <filename>erodouga_20sec_onishi_frame_56</filename>
                                    <path>/Users/yoheitaonishi/Downloads/JPEGImages/erodouga_20sec_onishi_frame_56.jpg</path>
                                    <source>
                                        <database>Unknown</database>
                                    </source>
                                    <size>
                                        <width>1280</width>
                                        <height>720</height>
                                        <depth>3</depth>
                                    </size>
                                    <segmented>0</segmented>
                                    <object>
                                            <name>pennis</name>
                                            <pose>Unspecified</pose>
                                            <truncated>0</truncated>
                                            <difficult>0</difficult>
                                            <bndbox>
                                                <xmin>95.25380710659898</xmin>
                                                <ymin>330.12267343485615</ymin>
                                                <xmax>315.90947546531305</xmax>
                                                <ymax>653.5152284263959</ymax>
                                            </bndbox>
                                    </object>
                                    
                                    <object>
                                            <name>vagina</name>
                                            <pose>Unspecified</pose>
                                            <truncated>0</truncated>
                                            <difficult>0</difficult>
                                            <bndbox>
                                                <xmin>269.8900169204738</xmin>
                                                <ymin>568.2445008460237</ymin>
                                                <xmax>370.3976311336718</xmax>
                                                <ymax>642.0304568527919</ymax>
                                            </bndbox>
                                    </object>
                                    </annotation>