<annotation verified="yes">
                                    <folder>Annotation</folder>
                                    <filename>erodouga_20sec_onishi_frame_66</filename>
                                    <path>/Users/yoheitaonishi/Downloads/JPEGImages/erodouga_20sec_onishi_frame_66.jpg</path>
                                    <source>
                                        <database>Unknown</database>
                                    </source>
                                    <size>
                                        <width>1280</width>
                                        <height>720</height>
                                        <depth>3</depth>
                                    </size>
                                    <segmented>0</segmented>
                                    <object>
                                            <name>pennis</name>
                                            <pose>Unspecified</pose>
                                            <truncated>0</truncated>
                                            <difficult>0</difficult>
                                            <bndbox>
                                                <xmin>104.54314720812182</xmin>
                                                <ymin>376.8570219966159</ymin>
                                                <xmax>335.909475465313</xmax>
                                                <ymax>674.7842639593908</ymax>
                                            </bndbox>
                                    </object>
                                    
                                    <object>
                                            <name>vagina</name>
                                            <pose>Unspecified</pose>
                                            <truncated>0</truncated>
                                            <difficult>0</difficult>
                                            <bndbox>
                                                <xmin>220.55414551607444</xmin>
                                                <ymin>591.5270727580372</ymin>
                                                <xmax>355.9813874788494</xmax>
                                                <ymax>672.2715736040609</ymax>
                                            </bndbox>
                                    </object>
                                    </annotation>